china_idiom/__init__.py
china_idiom/constants.py
china_idiom/core.py
china_idiom/idiom.csv
china_idiom-0.0.3.dist-info/LICENSE
china_idiom-0.0.3.dist-info/METADATA
china_idiom-0.0.3.dist-info/WHEEL
china_idiom-0.0.3.dist-info/top_level.txt
china_idiom-0.0.3.dist-info/RECORD
