Metadata-Version: 2.1
Name: china-idiom
Version: 0.0.3
Summary: 成语与成语接龙查询工具
Home-page: https://github.com/sfyc23/China-idiom
Author: sfyc23
Author-email: sfyc23@gmail.com
License: MIT
Keywords: China,idiom,成语,成语接龙,成语大全
Platform: UNKNOWN
Classifier: License :: OSI Approved :: MIT License
Classifier: Operating System :: MacOS
Classifier: Operating System :: Microsoft
Classifier: Operating System :: POSIX
Classifier: Operating System :: Unix
Classifier: Programming Language :: Python
Classifier: Programming Language :: Python :: 3
Classifier: Programming Language :: Python :: 3.6
Classifier: Programming Language :: Python :: Implementation :: CPython
Classifier: Programming Language :: Python :: Implementation :: PyPy
Requires-Python: >=3.6.0
Requires-Dist: pandas (>=0.23.4)
